adb_chix/__init__.py
adb_chix/app.py
adb_chix/templates/addlist.html
adb_chix/templates/index.html
adb_chix/templates/setlevel.html
adb_chix-0.3.dist-info/METADATA
adb_chix-0.3.dist-info/WHEEL
adb_chix-0.3.dist-info/entry_points.txt
adb_chix-0.3.dist-info/top_level.txt
adb_chix-0.3.dist-info/RECORD
