Metadata-Version: 2.4
Name: adb-chix
Version: 0.3
Requires-Dist: flask
Dynamic: description
Dynamic: description-content-type
Dynamic: requires-dist
